README.txt
setup.py
Products/__init__.py
Products/__init__.pyc
Products.PloneboardPortlet.egg-info/PKG-INFO
Products.PloneboardPortlet.egg-info/SOURCES.txt
Products.PloneboardPortlet.egg-info/dependency_links.txt
Products.PloneboardPortlet.egg-info/entry_points.txt
Products.PloneboardPortlet.egg-info/namespace_packages.txt
Products.PloneboardPortlet.egg-info/not-zip-safe
Products.PloneboardPortlet.egg-info/requires.txt
Products.PloneboardPortlet.egg-info/top_level.txt
Products/PloneboardPortlet/__init__.py
Products/PloneboardPortlet/changes.txt
Products/PloneboardPortlet/configure.zcml
Products/PloneboardPortlet/ploneboardportlet.pt
Products/PloneboardPortlet/ploneboardportlet.py
Products/PloneboardPortlet/readme.txt
Products/PloneboardPortlet/skins.zcml
Products/PloneboardPortlet/version.txt
Products/PloneboardPortlet/vocabularies.py
Products/PloneboardPortlet/_darcs/format
Products/PloneboardPortlet/_darcs/hashed_inventory
Products/PloneboardPortlet/_darcs/index_invalid
Products/PloneboardPortlet/_darcs/tentative_pristine
Products/PloneboardPortlet/_darcs/inventories/0000000186-22bc1feb600b7b56f23a864e74441f8807a40c5f942484e303dfead912193f49
Products/PloneboardPortlet/_darcs/inventories/0000000432-a1b94b01e490084bd03c6ee32ca423c7cd42bac30267c4365dde139a46ad0768
Products/PloneboardPortlet/_darcs/patches/0000001552-389f4e1ed571bbd9eaf665ef1fd859c283f42a608b492164d04c3ec307a67dd9
Products/PloneboardPortlet/_darcs/patches/0000019493-51bc6250e1cb4ba49a7746a375a536a127469c4d9d7adc2eb2066ae18524443b
Products/PloneboardPortlet/_darcs/patches/pending
Products/PloneboardPortlet/_darcs/patches/pending.tentative
Products/PloneboardPortlet/_darcs/prefs/author
Products/PloneboardPortlet/_darcs/prefs/binaries
Products/PloneboardPortlet/_darcs/prefs/boring
Products/PloneboardPortlet/_darcs/prefs/motd
Products/PloneboardPortlet/_darcs/pristine.hashed/0000000000-e3b0c44298fc1c149afbf4c8996fb92427ae41e4649b934ca495991b7852b855
Products/PloneboardPortlet/_darcs/pristine.hashed/0000000002-32c4858e22cc2c967b42150fa550562a2c839c2cebcaab91cabdf6f4da020022
Products/PloneboardPortlet/_darcs/pristine.hashed/0000000003-d0ff5974b6aa52cf562bea5921840c032a860a91a3512f7fe8f768f6bbe005f6
Products/PloneboardPortlet/_darcs/pristine.hashed/0000000063-e5a803bc305b68717ced59e22e77c470ace99527378d06dd77addbdb4458fbee
