Metadata-Version: 1.0
Name: Products.PloneboardPortlet
Version: 1.0.3b
Summary: An alternative ploneboard display portlet
Home-page: http://www.nidelven-it.no/d
Author: Nidelven IT
Author-email: info@nidelven-it.no
License: GPL
Keywords: python plone ploneboard portlet
Platform: UNKNOWN
Classifier: Programming Language :: Python
